README.md
setup.py
tezign.py
tezign.egg-info/PKG-INFO
tezign.egg-info/SOURCES.txt
tezign.egg-info/dependency_links.txt
tezign.egg-info/top_level.txt