Metadata-Version: 2.1
Name: tezign
Version: 0.1.0
Summary: Common python libs by Tezign
Home-page: UNKNOWN
Author: Anoyi
Author-email: 545544032@qq.com
License: UNKNOWN
Platform: UNKNOWN
Classifier: Programming Language :: Python :: 3
Classifier: License :: OSI Approved :: MIT License
Classifier: Operating System :: OS Independent
